{"version":1,"resource":"file:///home/mahin/.config/neofetch/config.conf","entries":[{"id":"dl64.conf","timestamp":1704636715236},{"id":"u9Il.conf","timestamp":1704636748813},{"id":"vCpU.conf","timestamp":1704636810068},{"id":"meVZ.conf","timestamp":1704636841010},{"id":"8t3i.conf","timestamp":1704636868354},{"id":"SYe9.conf","timestamp":1704636879893},{"id":"1RaN.conf","timestamp":1704636895220},{"id":"ZnyK.conf","source":"undoRedo.source","timestamp":1704636906455},{"id":"zfgV.conf","timestamp":1704636960336},{"id":"Ff0P.conf","source":"undoRedo.source","timestamp":1704636968548},{"id":"qsfP.conf","timestamp":1704637037316},{"id":"zQke.conf","timestamp":1704637146607}]}